f90nml/__init__.py
f90nml/cli.py
f90nml/findex.py
f90nml/fpy.py
f90nml/namelist.py
f90nml/parser.py
f90nml/scanner.py
f90nml/version.py
f90nml-1.5.0.dist-info/licenses/AUTHORS
f90nml-1.5.0.dist-info/licenses/LICENSE
f90nml-1.5.0.dist-info/licenses/NOTICE
tests/__init__.py
tests/test_f90nml.py
tests/test_scanner.py
f90nml-1.5.0.dist-info/METADATA
f90nml-1.5.0.dist-info/WHEEL
f90nml-1.5.0.dist-info/entry_points.txt
f90nml-1.5.0.dist-info/top_level.txt
f90nml-1.5.0.dist-info/RECORD
