Metadata-Version: 2.4
Name: f90nml
Version: 1.5.0
Summary: Fortran 90 namelist parser
Home-page: https://github.com/marshallward/f90nml
Author: Marshall Ward
Author-email: f90nml@marshallward.org
License: Apache-2.0
Classifier: Development Status :: 5 - Production/Stable
Classifier: License :: OSI Approved :: Apache Software License
Classifier: Programming Language :: Python :: 2
Classifier: Programming Language :: Python :: 2.7
Classifier: Programming Language :: Python :: 3
Classifier: Programming Language :: Python :: 3.6
Classifier: Programming Language :: Python :: 3.7
Classifier: Programming Language :: Python :: 3.8
Classifier: Programming Language :: Python :: 3.9
Classifier: Programming Language :: Python :: 3.10
Classifier: Programming Language :: Python :: 3.11
Classifier: Programming Language :: Python :: 3.12
Classifier: Programming Language :: Python :: 3.13
Classifier: Topic :: Utilities
License-File: LICENSE
License-File: NOTICE
License-File: AUTHORS
Provides-Extra: yaml
Requires-Dist: PyYAML; extra == "yaml"
Dynamic: license-file
